pymupump/__init__.py
pymupump/pymupump.py
pymupump-0.1.6.dist-info/METADATA
pymupump-0.1.6.dist-info/WHEEL
pymupump-0.1.6.dist-info/top_level.txt
pymupump-0.1.6.dist-info/RECORD
