Metadata-Version: 2.2
Name: pymupump
Version: 0.1.6
Summary: Python interface for controlling Harvard Apparatus Microliter OEM Syringe Pump
Author: Raphael Kriegl
Project-URL: Homepage, https://github.com/rk-exxec/pymupump
Project-URL: Issues, https://github.com/rk-exxec/pymupump/issues
Keywords: pump control,harvard apparatus,microliter OEM
Classifier: Development Status :: 4 - Beta
Classifier: Programming Language :: Python :: 3
Classifier: License :: OSI Approved :: GNU General Public License v3 or later (GPLv3+)
Requires-Python: >=3.6
Requires-Dist: pyserial
